AUTHORS
CHANGES.rst
LICENSE
MANIFEST.in
README.rst
auto_checklog.py
setup.py
pytest_autochecklog.egg-info/PKG-INFO
pytest_autochecklog.egg-info/SOURCES.txt
pytest_autochecklog.egg-info/dependency_links.txt
pytest_autochecklog.egg-info/entry_points.txt
pytest_autochecklog.egg-info/requires.txt
pytest_autochecklog.egg-info/top_level.txt